llm_bedrock_meta.py
llm_bedrock_meta-0.1.8.dist-info/LICENSE
llm_bedrock_meta-0.1.8.dist-info/METADATA
llm_bedrock_meta-0.1.8.dist-info/WHEEL
llm_bedrock_meta-0.1.8.dist-info/entry_points.txt
llm_bedrock_meta-0.1.8.dist-info/top_level.txt
llm_bedrock_meta-0.1.8.dist-info/RECORD
