Metadata-Version: 2.1
Name: llm-bedrock-meta
Version: 0.1.8
Summary: LLM plugin for Meta Llama2 on AWS Bedrock
Author: Fabian Labat
License: Apache-2.0
Project-URL: Homepage, https://github.com/flabat/llm-bedrock-meta
Classifier: License :: OSI Approved :: Apache Software License
License-File: LICENSE
Requires-Dist: llm
Requires-Dist: boto3 >=1.28.60
Provides-Extra: test
Requires-Dist: pytest ; extra == 'test'
